pyvbmc/__init__.py
pyvbmc/__main__.py
pyvbmc/acquisition_functions/README.md
pyvbmc/acquisition_functions/__init__.py
pyvbmc/acquisition_functions/abstract_acq_fcn.py
pyvbmc/acquisition_functions/acq_fcn.py
pyvbmc/acquisition_functions/acq_fcn_imiqr.py
pyvbmc/acquisition_functions/acq_fcn_log.py
pyvbmc/acquisition_functions/acq_fcn_noisy.py
pyvbmc/acquisition_functions/acq_fcn_vanilla.py
pyvbmc/acquisition_functions/acq_fcn_viqr.py
pyvbmc/acquisition_functions/utilities.py
pyvbmc/decorators/README.md
pyvbmc/decorators/__init__.py
pyvbmc/decorators/handle_0D_1D_input.py
pyvbmc/entropy/README.md
pyvbmc/entropy/__init__.py
pyvbmc/entropy/entlb_vbmc.py
pyvbmc/entropy/entmc_vbmc.py
pyvbmc/examples/pyvbmc_example_1_basic_usage.ipynb
pyvbmc/examples/pyvbmc_example_2_inputs_outputs.ipynb
pyvbmc/examples/pyvbmc_example_3_diagnostics_and_saving.ipynb
pyvbmc/examples/pyvbmc_example_4_validation.ipynb
pyvbmc/examples/pyvbmc_example_5_prior_distributions.ipynb
pyvbmc/examples/pyvbmc_example_6_noisy_likelihoods.ipynb
pyvbmc/examples/scripts/Makefile
pyvbmc/examples/scripts/pyvbmc_example_1_full_code.py
pyvbmc/examples/scripts/pyvbmc_example_2_full_code.py
pyvbmc/examples/scripts/pyvbmc_example_3_full_code.py
pyvbmc/examples/scripts/pyvbmc_example_4_full_code.py
pyvbmc/examples/scripts/pyvbmc_example_5_full_code.py
pyvbmc/examples/scripts/pyvbmc_example_6_full_code.py
pyvbmc/formatting/__init__.py
pyvbmc/formatting/formatting.py
pyvbmc/function_logger/README.md
pyvbmc/function_logger/__init__.py
pyvbmc/function_logger/function_logger.py
pyvbmc/parameter_transformer/README.md
pyvbmc/parameter_transformer/__init__.py
pyvbmc/parameter_transformer/parameter_transformer.py
pyvbmc/priors/__init__.py
pyvbmc/priors/convert_to_prior.py
pyvbmc/priors/prior.py
pyvbmc/priors/product.py
pyvbmc/priors/scipy.py
pyvbmc/priors/smooth_box.py
pyvbmc/priors/spline_trapezoidal.py
pyvbmc/priors/tile_inputs.py
pyvbmc/priors/trapezoidal.py
pyvbmc/priors/uniform_box.py
pyvbmc/priors/user_function.py
PyVBMC-1.0.4.dist-info/LICENSE
PyVBMC-1.0.4.dist-info/METADATA
PyVBMC-1.0.4.dist-info/WHEEL
PyVBMC-1.0.4.dist-info/top_level.txt
PyVBMC-1.0.4.dist-info/RECORD
